comodo_rest_api/__init__.py
comodo_rest_api-0.4.0.dist-info/LICENSE.txt
comodo_rest_api-0.4.0.dist-info/WHEEL
comodo_rest_api-0.4.0.dist-info/METADATA
comodo_rest_api-0.4.0.dist-info/RECORD
