Metadata-Version: 2.1
Name: comodo_rest_api
Version: 0.4.0
Summary: A simpler RESTful API for Comodo/Sectigo
Home-page: https://github.com/erinn/comodo_rest_api/
License: UNKNOWN
Keywords: sectigo comodo jsend
Author: Erinn Looney-Triggs
Author-email: erinn.looneytriggs@gmail.com
Requires-Python: >=3
Classifier: License :: OSI Approved :: GNU Affero General Public License v3 or later (AGPLv3+)
Classifier: Development Status :: 5 - Production/Stable
Requires-Dist: pyjsend
Requires-Dist: requests
